model_train_protocol/Protocol.py
model_train_protocol/__init__.py
model_train_protocol/prototyping.py
model_train_protocol/_internal/ProtocolFile.py
model_train_protocol/_internal/TemplateFile.py
model_train_protocol/_internal/__init__.py
model_train_protocol/common/__init__.py
model_train_protocol/common/constants.py
model_train_protocol/common/util.py
model_train_protocol/common/guardrails/Guardrail.py
model_train_protocol/common/guardrails/__init__.py
model_train_protocol/common/instructions/BaseInstruction.py
model_train_protocol/common/instructions/ExtendedInstruction.py
model_train_protocol/common/instructions/Instruction.py
model_train_protocol/common/instructions/__init__.py
model_train_protocol/common/prototyping/__init__.py
model_train_protocol/common/prototyping/entry.py
model_train_protocol/common/prototyping/translator.py
model_train_protocol/common/prototyping/utils.py
model_train_protocol/common/prototyping/providers/__init__.py
model_train_protocol/common/prototyping/providers/openai.py
model_train_protocol/common/pydantic/__init__.py
model_train_protocol/common/pydantic/protocol.py
model_train_protocol/common/pydantic/prototyping.py
model_train_protocol/common/tokens/NumListToken.py
model_train_protocol/common/tokens/NumToken.py
model_train_protocol/common/tokens/SpecialToken.py
model_train_protocol/common/tokens/Token.py
model_train_protocol/common/tokens/TokenSet.py
model_train_protocol/common/tokens/__init__.py
model_train_protocol-0.2.0.dist-info/licenses/LICENSE
model_train_protocol-0.2.0.dist-info/METADATA
model_train_protocol-0.2.0.dist-info/WHEEL
model_train_protocol-0.2.0.dist-info/top_level.txt
model_train_protocol-0.2.0.dist-info/RECORD
