Metadata-Version: 2.4
Name: model-train-protocol
Version: 0.2.0
Summary: Standardized protocol to train models on Databiomes
Author-email: "Databiomes Inc." <dev@databiomes.com>
Project-URL: Homepage, https://pypi.org/project/model-train-protocol/
Project-URL: Documentation, https://modeltrainprotocol.readthedocs.io/
Project-URL: Repository, https://github.com/databiomes/modeltrainprotocol
Project-URL: Issues, https://github.com/databiomes/modeltrainprotocol/issues
Classifier: Programming Language :: Python :: 3
Classifier: License :: OSI Approved :: Apache Software License
Classifier: Operating System :: OS Independent
Requires-Python: >=3.9
License-File: LICENSE
Requires-Dist: emoji>=2.8.0
Requires-Dist: pydantic>=2.0.0
Provides-Extra: test
Requires-Dist: requests>=2.0.0; extra == "test"
Requires-Dist: python-dotenv>=1.0.0; extra == "test"
Requires-Dist: pytest>=7.0.0; extra == "test"
Requires-Dist: pytest-cov>=4.0.0; extra == "test"
Requires-Dist: pytest-mock>=3.10.0; extra == "test"
Requires-Dist: pytest-xdist>=3.0.0; extra == "test"
Dynamic: license-file
